yesqa.py
yesqa-1.5.0.dist-info/LICENSE
yesqa-1.5.0.dist-info/METADATA
yesqa-1.5.0.dist-info/WHEEL
yesqa-1.5.0.dist-info/entry_points.txt
yesqa-1.5.0.dist-info/top_level.txt
yesqa-1.5.0.dist-info/RECORD
