Metadata-Version: 2.1
Name: yesqa
Version: 1.5.0
Summary: Automatically remove unnecessary `# noqa` comments.
Home-page: https://github.com/asottile/yesqa
Author: Anthony Sottile
Author-email: asottile@umich.edu
License: MIT
Classifier: License :: OSI Approved :: MIT License
Classifier: Programming Language :: Python :: 3
Classifier: Programming Language :: Python :: 3 :: Only
Classifier: Programming Language :: Python :: Implementation :: CPython
Classifier: Programming Language :: Python :: Implementation :: PyPy
Requires-Python: >=3.8
License-File: LICENSE
Requires-Dist: flake8 (>=3.9)
Requires-Dist: tokenize-rt (>=2.1)
